pandas_fuzz/__init__.py
pandas_fuzz/pdfuzz.json
pandas_fuzz/pdfuzz.py
pandas_fuzz-0.1.4.dist-info/LICENSE
pandas_fuzz-0.1.4.dist-info/METADATA
pandas_fuzz-0.1.4.dist-info/WHEEL
pandas_fuzz-0.1.4.dist-info/RECORD
