Metadata-Version: 2.1
Name: pandas-fuzz
Version: 0.1.4
Summary: Extension for `pandas` to use `rapidfuzz` for fuzzy matching.
License: MIT
Keywords: pandas,rapidfuzz
Author: Christoph Dörrer
Author-email: d-chris@web.de
Requires-Python: >=3.9,<4.0
Classifier: License :: OSI Approved :: MIT License
Classifier: Operating System :: OS Independent
Classifier: Programming Language :: Python :: 3
Classifier: Programming Language :: Python :: 3.9
Classifier: Programming Language :: Python :: 3.10
Classifier: Programming Language :: Python :: 3.11
Classifier: Programming Language :: Python :: 3.12
Classifier: Programming Language :: Python :: 3.13
Requires-Dist: pandas (>=2.2.2,<3.0.0)
Requires-Dist: rapidfuzz (>=3.9.4,<4.0.0)
Project-URL: documentation, https://d-chris.github.io/pandas_fuzz
Project-URL: repository, https://github.com/d-chris/pandas_fuzz
